{
  "version": "7",
  "dialect": "sqlite",
  "entries": [
    {
      "idx": 0,
      "version": "6",
      "when": 1784172347106,
      "tag": "0000_empty_warhawk",
      "breakpoints": true
    },
    {
      "idx": 1,
      "version": "6",
      "when": 1784178111251,
      "tag": "0001_melodic_layla_miller",
      "breakpoints": true
    },
    {
      "idx": 2,
      "version": "6",
      "when": 1784211018764,
      "tag": "0002_familiar_morg",
      "breakpoints": true
    },
    {
      "idx": 3,
      "version": "6",
      "when": 1784215310378,
      "tag": "0003_plain_wiccan",
      "breakpoints": true
    },
    {
      "idx": 4,
      "version": "6",
      "when": 1784217146368,
      "tag": "0004_typical_fallen_one",
      "breakpoints": true
    },
    {
      "idx": 5,
      "version": "6",
      "when": 1784262717818,
      "tag": "0005_lethal_serpent_society",
      "breakpoints": true
    },
    {
      "idx": 6,
      "version": "6",
      "when": 1784264075524,
      "tag": "0006_kind_whirlwind",
      "breakpoints": true
    },
    {
      "idx": 7,
      "version": "6",
      "when": 1784264098885,
      "tag": "0007_organic_yellowjacket",
      "breakpoints": true
    },
    {
      "idx": 8,
      "version": "6",
      "when": 1784275906476,
      "tag": "0008_dry_naoko",
      "breakpoints": true
    },
    {
      "idx": 9,
      "version": "6",
      "when": 1784278308202,
      "tag": "0009_sudden_slyde",
      "breakpoints": true
    },
    {
      "idx": 10,
      "version": "6",
      "when": 1784278662858,
      "tag": "0010_red_pestilence",
      "breakpoints": true
    },
    {
      "idx": 11,
      "version": "6",
      "when": 1784284447745,
      "tag": "0011_quiet_red_wolf",
      "breakpoints": true
    },
    {
      "idx": 12,
      "version": "6",
      "when": 1784298147044,
      "tag": "0012_greedy_jamie_braddock",
      "breakpoints": true
    },
    {
      "idx": 13,
      "version": "6",
      "when": 1784301415254,
      "tag": "0013_moaning_anita_blake",
      "breakpoints": true
    },
    {
      "idx": 14,
      "version": "6",
      "when": 1784304560029,
      "tag": "0014_chemical_mac_gargan",
      "breakpoints": true
    },
    {
      "idx": 15,
      "version": "6",
      "when": 1784312950143,
      "tag": "0015_organic_excalibur",
      "breakpoints": true
    }
  ]
}
